episemic/__init__.py
episemic/api.py
episemic/cli/__init__.py
episemic/cli/main.py
episemic/config.py
episemic/consolidation/__init__.py
episemic/consolidation/consolidation.py
episemic/cortex/__init__.py
episemic/cortex/cortex.py
episemic/hippocampus/__init__.py
episemic/hippocampus/duckdb_hippocampus.py
episemic/hippocampus/hippocampus.py
episemic/models.py
episemic/retrieval/__init__.py
episemic/retrieval/retrieval.py
episemic/simple.py
episemic-1.0.3.dist-info/METADATA
episemic-1.0.3.dist-info/WHEEL
episemic-1.0.3.dist-info/entry_points.txt
episemic-1.0.3.dist-info/licenses/LICENSE
episemic-1.0.3.dist-info/RECORD
