Metadata-Version: 2.4
Name: episemic
Version: 1.0.3
Summary: A brain-inspired memory system for AI agents
License: MIT
License-File: LICENSE
Keywords: ai,memory,agents,brain-inspired,vector-database
Author: Aditya Karnam
Author-email: akarnam37@gmail.com
Requires-Python: >=3.11
Classifier: Development Status :: 3 - Alpha
Classifier: Intended Audience :: Developers
Classifier: License :: OSI Approved :: MIT License
Classifier: Programming Language :: Python :: 3
Classifier: Programming Language :: Python :: 3.11
Classifier: Programming Language :: Python :: 3.12
Classifier: Topic :: Scientific/Engineering :: Artificial Intelligence
Classifier: Topic :: Software Development :: Libraries :: Python Modules
Requires-Dist: duckdb (>=1.4.0)
Requires-Dist: psycopg2-binary (>=2.9.0)
Requires-Dist: pydantic (>=2.11.0)
Requires-Dist: qdrant-client (>=1.15.0)
Requires-Dist: redis (>=6.0.0)
Requires-Dist: rich (>=14.0.0)
Requires-Dist: sentence-transformers (>=5.0.0)
Requires-Dist: typer (>=0.18.0)
Project-URL: Bug Tracker, https://github.com/episemic/episemic/issues
Project-URL: Documentation, https://episemic.readthedocs.io
Project-URL: Homepage, https://github.com/episemic/episemic
Project-URL: Repository, https://github.com/episemic/episemic
